README
setup.py
pyar/__init__.py
pyar/exc.py
pyar/result.py
pyar/settings.py
pyar/url.py
pyar/util.py
pyar/version.py
pyar.egg-info/PKG-INFO
pyar.egg-info/SOURCES.txt
pyar.egg-info/dependency_links.txt
pyar.egg-info/requires.txt
pyar.egg-info/top_level.txt
pyar/dialects/__init__.py
pyar/dialects/connection.py
pyar/dialects/mysql/__init__.py
pyar/dialects/mysql/base.py
pyar/dialects/postgresql/__init__.py
pyar/dialects/postgresql/base.py
pyar/dialects/sqlite/__init__.py
pyar/dialects/sqlite/base.py
pyar/scripts/test.py