Metadata-Version: 1.0
Name: pyar
Version: 0.2.1
Summary: pyar sqlhelper based sqlbuilder.
Home-page: http://www.penqie.com
Author: Jefurry
Author-email: jefurry@qq.com
License: LGPL
Keywords: pyar sqlwrapper sqlhelper
Platform: UNKNOWN
